ga4_analytics/__init__.py
ga4_analytics/processor.py
ga4_analytics_processor-0.2.0.dist-info/licenses/LICENSE
ga4_analytics_processor-0.2.0.dist-info/METADATA
ga4_analytics_processor-0.2.0.dist-info/WHEEL
ga4_analytics_processor-0.2.0.dist-info/top_level.txt
ga4_analytics_processor-0.2.0.dist-info/RECORD
